{"cameraMode":{"drawMode":0,"name":"Shaded","section":"Shading Mode"},"sceneLighting":true,"audioPlay":false,"sceneViewState":{"showFog":true,"showMaterialUpdate":false,"showSkybox":true,"showFlares":true,"showImageEffects":true,"showParticleSystems":true},"in2DMode":false,"pivot":{"x":110.65865325927735,"y":67.93672180175781,"z":47.88960266113281},"rotation":{"x":0.08584330976009369,"y":0.9045310616493225,"z":-0.2179061323404312,"w":0.35635900497436526},"size":43.708953857421878,"orthographic":false}